AUTHORS.rst
CONTRIBUTING.rst
HISTORY.rst
LICENSE
MANIFEST.in
README.rst
setup.cfg
setup.py
docker_registry_cleanup/__init__.py
docker_registry_cleanup/cli.py
docker_registry_cleanup/docker_registry_cleanup.py
docker_registry_cleanup.egg-info/PKG-INFO
docker_registry_cleanup.egg-info/SOURCES.txt
docker_registry_cleanup.egg-info/dependency_links.txt
docker_registry_cleanup.egg-info/entry_points.txt
docker_registry_cleanup.egg-info/not-zip-safe
docker_registry_cleanup.egg-info/requires.txt
docker_registry_cleanup.egg-info/top_level.txt
docs/Makefile
docs/authors.rst
docs/conf.py
docs/contributing.rst
docs/history.rst
docs/index.rst
docs/installation.rst
docs/make.bat
docs/readme.rst
docs/usage.rst
tests/__init__.py
tests/test_docker_registry_cleanup.py