Metadata-Version: 1.2
Name: docker-registry-cleanup
Version: 0.1.0
Summary: Cleanup images in a docker registry
Home-page: https://github.com/renefritze/docker_registry_cleanup
Author: René Fritze
Author-email: rene@fritze.me
License: BSD license
Keywords: docker_registry_cleanup
Platform: UNKNOWN
Classifier: Development Status :: 2 - Pre-Alpha
Classifier: Intended Audience :: Developers
Classifier: License :: OSI Approved :: BSD License
Classifier: Natural Language :: English
Classifier: Programming Language :: Python :: 3
Classifier: Programming Language :: Python :: 3.5
Classifier: Programming Language :: Python :: 3.6
Classifier: Programming Language :: Python :: 3.7
Classifier: Programming Language :: Python :: 3.8
Requires-Python: >=3.5
